_prox_tv
prox_tv
